README.rst
pyfuncrun.py
setup.py
pyfuncrun.egg-info/PKG-INFO
pyfuncrun.egg-info/SOURCES.txt
pyfuncrun.egg-info/dependency_links.txt
pyfuncrun.egg-info/entry_points.txt
pyfuncrun.egg-info/top_level.txt