Metadata-Version: 1.0
Name: pyfuncrun
Version: 0.1.5
Summary: A tool to run a python function in a module from command line
Home-page: https://github.com/zhangliyong/pyfuncrun
Author: Lyon Zhang
Author-email: lyzhang87@gmail.com
License: BSD
Platform: UNKNOWN
